<?xml version="1.0" encoding="UTF-8"?>
<objects serializationModel="Studio.02.01.00">
	<object class="Event" id="{55f93c2e-a0fd-4384-a8de-d3147ae55077}">
		<property name="name">
			<value>sfx_enemy_death</value>
		</property>
		<property name="outputFormat">
			<value>1</value>
		</property>
		<relationship name="folder">
			<destination>{e2cd88a6-262f-4967-865b-25c8e3680efb}</destination>
		</relationship>
		<relationship name="mixer">
			<destination>{84e769c9-9c7c-4d1d-bb0e-dd0b9210596a}</destination>
		</relationship>
		<relationship name="masterTrack">
			<destination>{28a51d8d-1abe-49ce-b6b9-496d19c1b691}</destination>
		</relationship>
		<relationship name="mixerInput">
			<destination>{cbd02e63-8dee-425e-b630-2276c02222e5}</destination>
		</relationship>
		<relationship name="automatableProperties">
			<destination>{194e9c7c-d4a8-4109-a2a2-00ff62eda509}</destination>
		</relationship>
		<relationship name="markerTracks">
			<destination>{ed74230f-3150-46b2-ab02-32d6a2481d69}</destination>
		</relationship>
		<relationship name="groupTracks">
			<destination>{c2c28cbc-8d39-4510-8f03-6cd520c6a84b}</destination>
			<destination>{5bb64f8b-9023-4460-9105-e3c143e1189c}</destination>
		</relationship>
		<relationship name="timeline">
			<destination>{2e2a9003-3439-4741-8883-5b6a02ba2290}</destination>
		</relationship>
		<relationship name="banks">
			<destination>{04df0362-25d3-4392-8b6b-db5b65c138d0}</destination>
		</relationship>
	</object>
	<object class="EventMixer" id="{84e769c9-9c7c-4d1d-bb0e-dd0b9210596a}">
		<relationship name="masterBus">
			<destination>{93554bc5-3689-4f26-8684-84ff8e631cbd}</destination>
		</relationship>
	</object>
	<object class="MasterTrack" id="{28a51d8d-1abe-49ce-b6b9-496d19c1b691}">
		<relationship name="mixerGroup">
			<destination>{93554bc5-3689-4f26-8684-84ff8e631cbd}</destination>
		</relationship>
	</object>
	<object class="MixerInput" id="{cbd02e63-8dee-425e-b630-2276c02222e5}">
		<relationship name="effectChain">
			<destination>{15a82a94-2c41-4b1f-919e-f0a84d2ab0b6}</destination>
		</relationship>
		<relationship name="panner">
			<destination>{37a0ebde-4cda-4b04-b9d2-8433179b68d1}</destination>
		</relationship>
		<relationship name="output">
			<destination>{3eeecec0-7e13-4776-80a9-724fec8cc7da}</destination>
		</relationship>
	</object>
	<object class="EventAutomatableProperties" id="{194e9c7c-d4a8-4109-a2a2-00ff62eda509}" />
	<object class="MarkerTrack" id="{ed74230f-3150-46b2-ab02-32d6a2481d69}" />
	<object class="GroupTrack" id="{c2c28cbc-8d39-4510-8f03-6cd520c6a84b}">
		<relationship name="modules">
			<destination>{2ebdb3b7-a1e2-45fb-b5db-5f54bebb7b3c}</destination>
		</relationship>
		<relationship name="mixerGroup">
			<destination>{52c605a9-6cd5-4761-9924-174d4810f9cf}</destination>
		</relationship>
	</object>
	<object class="GroupTrack" id="{5bb64f8b-9023-4460-9105-e3c143e1189c}">
		<relationship name="modules">
			<destination>{225f8a79-209d-45f4-9b75-e8bc6bbb17c7}</destination>
		</relationship>
		<relationship name="mixerGroup">
			<destination>{f7a3a6e0-85f0-41ef-8309-c292201da55d}</destination>
		</relationship>
	</object>
	<object class="Timeline" id="{2e2a9003-3439-4741-8883-5b6a02ba2290}">
		<relationship name="modules">
			<destination>{2ebdb3b7-a1e2-45fb-b5db-5f54bebb7b3c}</destination>
			<destination>{225f8a79-209d-45f4-9b75-e8bc6bbb17c7}</destination>
		</relationship>
	</object>
	<object class="EventMixerMaster" id="{93554bc5-3689-4f26-8684-84ff8e631cbd}">
		<property name="volume">
			<value>3</value>
		</property>
		<relationship name="effectChain">
			<destination>{e11636d7-59e2-4ed0-a3f5-08a7118e4a94}</destination>
		</relationship>
		<relationship name="panner">
			<destination>{972b9299-7db6-4d86-a395-896f7c3292b3}</destination>
		</relationship>
		<relationship name="mixer">
			<destination>{84e769c9-9c7c-4d1d-bb0e-dd0b9210596a}</destination>
		</relationship>
	</object>
	<object class="MixerBusEffectChain" id="{15a82a94-2c41-4b1f-919e-f0a84d2ab0b6}">
		<relationship name="effects">
			<destination>{62e89881-baf7-465c-af17-309f4a8cd588}</destination>
		</relationship>
	</object>
	<object class="MixerBusPanner" id="{37a0ebde-4cda-4b04-b9d2-8433179b68d1}" />
	<object class="MultiSound" id="{2ebdb3b7-a1e2-45fb-b5db-5f54bebb7b3c}">
		<property name="triggerProbabilityEnabled">
			<value>true</value>
		</property>
		<property name="triggerProbability">
			<value>58</value>
		</property>
		<property name="length">
			<value>0.66666666666666663</value>
		</property>
		<relationship name="modulators">
			<destination>{6bd73153-4599-432c-b56c-5cf17790b203}</destination>
		</relationship>
		<relationship name="sounds">
			<destination>{1fa6bb92-b006-415c-82fa-6a7f2d37f123}</destination>
			<destination>{abdf575c-6d4c-4097-b831-f09f472cad01}</destination>
		</relationship>
	</object>
	<object class="EventMixerGroup" id="{52c605a9-6cd5-4761-9924-174d4810f9cf}">
		<property name="volume">
			<value>-3</value>
		</property>
		<property name="name">
			<value>Audio 1</value>
		</property>
		<relationship name="effectChain">
			<destination>{6569add7-2c43-4d4f-ad1a-c6acf5817ab8}</destination>
		</relationship>
		<relationship name="panner">
			<destination>{cc71a170-e024-45df-bc75-83a85dd5d702}</destination>
		</relationship>
		<relationship name="output">
			<destination>{93554bc5-3689-4f26-8684-84ff8e631cbd}</destination>
		</relationship>
	</object>
	<object class="SingleSound" id="{225f8a79-209d-45f4-9b75-e8bc6bbb17c7}">
		<property name="length">
			<value>1.3333333333333333</value>
		</property>
		<relationship name="modulators">
			<destination>{6722396b-396a-493e-acd2-e6fba71c90c3}</destination>
		</relationship>
		<relationship name="audioFile">
			<destination>{884fe2d2-5a10-460c-896c-31f3d9d1a551}</destination>
		</relationship>
	</object>
	<object class="EventMixerGroup" id="{f7a3a6e0-85f0-41ef-8309-c292201da55d}">
		<property name="volume">
			<value>-2</value>
		</property>
		<property name="name">
			<value>Audio 2</value>
		</property>
		<relationship name="effectChain">
			<destination>{1578e55b-9cec-4da3-9af0-a40cb356d7d2}</destination>
		</relationship>
		<relationship name="panner">
			<destination>{a14a2d0d-88da-47de-a188-627ebe5d7d4c}</destination>
		</relationship>
		<relationship name="output">
			<destination>{93554bc5-3689-4f26-8684-84ff8e631cbd}</destination>
		</relationship>
	</object>
	<object class="MixerBusEffectChain" id="{e11636d7-59e2-4ed0-a3f5-08a7118e4a94}">
		<relationship name="effects">
			<destination>{7507ab73-09bf-4f20-bc5e-ddb0a709cd9a}</destination>
		</relationship>
	</object>
	<object class="MixerBusPanner" id="{972b9299-7db6-4d86-a395-896f7c3292b3}" />
	<object class="MixerBusFader" id="{62e89881-baf7-465c-af17-309f4a8cd588}" />
	<object class="RandomizerModulator" id="{6bd73153-4599-432c-b56c-5cf17790b203}">
		<property name="nameOfPropertyBeingModulated">
			<value>pitch</value>
		</property>
		<property name="amount">
			<value>3</value>
		</property>
	</object>
	<object class="SingleSound" id="{1fa6bb92-b006-415c-82fa-6a7f2d37f123}">
		<relationship name="audioFile">
			<destination>{6b221c6d-7807-4b11-b34e-12c4d2f270c7}</destination>
		</relationship>
	</object>
	<object class="SingleSound" id="{abdf575c-6d4c-4097-b831-f09f472cad01}">
		<relationship name="audioFile">
			<destination>{24cc7003-e502-4ec3-a30e-511d388cbccd}</destination>
		</relationship>
	</object>
	<object class="MixerBusEffectChain" id="{6569add7-2c43-4d4f-ad1a-c6acf5817ab8}">
		<relationship name="effects">
			<destination>{bd3a8141-7608-4bda-ae56-9b7d75de7941}</destination>
		</relationship>
	</object>
	<object class="MixerBusPanner" id="{cc71a170-e024-45df-bc75-83a85dd5d702}" />
	<object class="RandomizerModulator" id="{6722396b-396a-493e-acd2-e6fba71c90c3}">
		<property name="nameOfPropertyBeingModulated">
			<value>pitch</value>
		</property>
		<property name="amount">
			<value>10</value>
		</property>
	</object>
	<object class="MixerBusEffectChain" id="{1578e55b-9cec-4da3-9af0-a40cb356d7d2}">
		<relationship name="effects">
			<destination>{c01db89c-0d87-4337-aa09-36b2faef3241}</destination>
		</relationship>
	</object>
	<object class="MixerBusPanner" id="{a14a2d0d-88da-47de-a188-627ebe5d7d4c}" />
	<object class="MixerBusFader" id="{7507ab73-09bf-4f20-bc5e-ddb0a709cd9a}" />
	<object class="MixerBusFader" id="{bd3a8141-7608-4bda-ae56-9b7d75de7941}" />
	<object class="MixerBusFader" id="{c01db89c-0d87-4337-aa09-36b2faef3241}" />
</objects>
